graphmeun/__init__.py
graphmeun/graphMenu.py
graphmenu-1.0.1.dist-info/COPYING.txt
graphmenu-1.0.1.dist-info/METADATA
graphmenu-1.0.1.dist-info/WHEEL
graphmenu-1.0.1.dist-info/top_level.txt
graphmenu-1.0.1.dist-info/RECORD
