Metadata-Version: 2.1
Name: graphmenu
Version: 1.0.1
Summary: some code
Home-page: https://github.com/exclusive1214/Law_ChatBot
Author: BensonKAO
Author-email: bonson930235@gmail.com
License: MIT
Platform: UNKNOWN
Classifier: Development Status :: 5 - Production/Stable
Classifier: License :: OSI Approved :: MIT License
Classifier: Programming Language :: Python
Requires-Dist: psycopg2-binary
